adlermanager/AdlerManagerSSHProtocol.py
adlermanager/AdlerManagerTokenResource.py
adlermanager/Config.py
adlermanager/IncidentManager.py
adlermanager/SitesManager.py
adlermanager/TokenResource.py
adlermanager/WebRoot.py
adlermanager/__init__.py
adlermanager/__main__.py
adlermanager/_version.py
adlermanager/conch_helpers.py
adlermanager/model.py
adlermanager/motd.txt
adlermanager/utils.py
adlermanager/templates/template.j2
adlermanager/vendor/bootstrap.bundle.min.js
adlermanager/vendor/bootstrap.min.css
adlermanager-25.4.0.dist-info/METADATA
adlermanager-25.4.0.dist-info/WHEEL
adlermanager-25.4.0.dist-info/entry_points.txt
adlermanager-25.4.0.dist-info/licenses/LICENSE
adlermanager-25.4.0.dist-info/RECORD
