Metadata-Version: 2.4
Name: adlermanager
Version: 25.4.0
Summary: A self-hostable status webpage that uses Prometheus alerts to create and maintain service status and incident tracking / customer information flow.
Project-URL: Changelog, https://farga.exo.cat/exo/prometheus-adlermanager/commits/branch/main
Project-URL: Documentation, https://farga.exo.cat/exo/prometheus-adlermanager/
Project-URL: Homepage, https://farga.exo.cat/exo/prometheus-adlermanager/
Project-URL: Issues, https://farga.exo.cat/exo/prometheus-adlermanager/issues
Project-URL: Source, https://farga.exo.cat/exo/prometheus-adlermanager/
Author-email: Evilham <cvs@evilham.com>
License: MIT License
License-File: LICENSE
Classifier: Programming Language :: Python :: 3
Classifier: Programming Language :: Python :: 3 :: Only
Classifier: Programming Language :: Python :: 3.8
Classifier: Programming Language :: Python :: 3.9
Classifier: Programming Language :: Python :: 3.10
Classifier: Programming Language :: Python :: 3.11
Classifier: Programming Language :: Python :: 3.12
Requires-Python: >=3.8.0
Requires-Dist: attrs>=21.3.0
Requires-Dist: jinja2>=3.1.0
Requires-Dist: klein>=22.0.0
Requires-Dist: markdown>=3.5.0
Requires-Dist: pyyaml>=6.0.0
Requires-Dist: twisted[conch]>=22.0.0
